{"name":"PhantomJS for ARM","tagline":"PhantomJS 2.0.0 compiled for armv7","body":"# phantomjs-2.0.0-armv7\r\nCompiled for armv7\r\n\r\n# Dependencies\r\n\r\nFor Debian-based distros:\r\n\r\n`sudo apt-get install flex bison gperf ruby perl libsqlite3-dev libfontconfig1-dev libicu-dev libfreetype6 libssl-dev libpng-dev libjpeg-dev python libX11-dev libxext-dev`\r\n\r\n# Download\r\n\r\n`wget https://github.com/dhamaniasad/phantomjs-2.0.0-armv7/raw/master/phantomjs`\r\n\r\n`https://github.com/dhamaniasad/phantomjs-2.0.0-armv7/raw/master/phantomjs_jessie`\r\n(Compiled for Debian Jessie)","google":"","note":"Don't delete this file! It's used internally to help with page regeneration."}